kedro_dolt/__init__.py
kedro_dolt/hook.py
kedro_dolt-0.1.0.dist-info/WHEEL
kedro_dolt-0.1.0.dist-info/METADATA
kedro_dolt-0.1.0.dist-info/RECORD
